Workbook

Sheet Dashboard
A1: PRODUCT SALES REGION - ADVANCED 5.2 FIXED AUDITED | Plain Range Formulas Data!B2:B1501 - No Structured Ref = No #REF! | 15 Charts | Full Screen Alt+W+L
A3: Total Revenue | D3: Total Qty | G3: Avg Discount | J3: Return Rate | M3: Total Orders | P3: ⛶ FULL SCREEN (Alt+W+L)
A4: =SUM(Data!J2:J1501) | D4: =SUM(Data!D2:D1501) | G4: =AVERAGE(Data!H2:H1501) | J4: =SUM(Data!M2:M1501)/COUNTA(Data!M2:M1501) | M4: =COUNTA(Data!N2:N1501) | P4: Go to Data | Q4: Go to Analytics

Sheet Data
A1: Date | B1: Region | C1: Product | D1: Quantity | E1: UnitPrice | F1: StoreLocation | G1: CustomerType | H1: Discount | I1: Salesperson | J1: TotalPrice | K1: PaymentMethod | L1: Promotion | M1: Returned | N1: OrderID | O1: CustomerName | P1: ShippingCost | Q1: OrderDate | R1: DeliveryDate | S1: RegionManager | T1: YearMonth
A2: 44980 | B2: East | C2: Laptop | D2: 14 | E2: 163.6 | F2: Store B | G2: Wholesale | H2: 0 | I2: Eva | J2: 2290.4 | K2: Online | L2: FREESHIP | M2: 0 | N2: REG100000 | O2: Cust 6583 | P2: 43.34 | Q2: 44980 | R2: 44984 | S2: Eric | T2: 2023-02
A3: 45645 | B3: South | C3: Phone | D3: 1 | E3: 544.01 | F3: Store A | G3: Retail | H3: 0 | I3: Alice | J3: 544.01 | K3: Gift Card | L3: SAVE10 | M3: 0 | N3: REG100001 | O3: Cust 2144 | P3: 5.3 | Q3: 45645 | R3: 45654 | S3: Sophie | T3: 2024-12
A4: 45056 | B4: North | C4: Desk | D4: 14 | E4: 346.18 | F4: Store B | G4: Wholesale | H4: 0.1 | I4: Alice | J4: 4361.868 | K4: Online | L4: WINTER15 | M4: 0 | N4: REG100002 | O4: Cust 5998 | P4: 20.46 | Q4: 45056 | R4: 45065 | S4: Ryan | T4: 2023-05
A5: 45714 | B5: Central | C5: Chair | D5: 18 | E5: 384.82 | F5: Store A | G5: Wholesale | H5: 0.15 | I5: Frank | J5: 5887.746 | K5: Gift Card | L5: FREESHIP | M5: 0 | N5: REG100003 | O5: Cust 7136 | P5: 27.95 | Q5: 45714 | R5: 45718 | S5: Cameron | T5: 2025-02
A6: 45101 | B6: East | C6: Desk | D6: 18 | E6: 237.76 | F6: Store C | G6: Retail | H6: 0 | I6: Carlos | J6: 4279.68 | K6: Online | L6: SAVE10 | M6: 0 | N6: REG100004 | O6: Cust 6506 | P6: 5.73 | Q6: 45101 | R6: 45104 | S6: Eric | T6: 2023-06
A7: 45342 | B7: Central | C7: Monitor | D7: 2 | E7: 385.09 | F7: Store D | G7: Wholesale | H7: 0.15 | I7: Diana | J7: 654.653 | K7: Credit Card | M7: 0 | N7: REG100005 | O7: Cust 3909 | P7: 11.92 | Q7: 45342 | R7: 45352 | S7: Cameron | T7: 2024-02
A8: 44937 | B8: South | C8: Chair | D8: 7 | E8: 17.5 | F8: Store C | G8: Retail | H8: 0.1 | I8: Alice | J8: 110.25 | K8: Debit Card | L8: WINTER15 | M8: 0 | N8: REG100006 | O8: Cust 7887 | P8: 5.02 | Q8: 44937 | R8: 44940 | S8: Sophie | T8: 2023-01
A9: 44935 | B9: Central | C9: Chair | D9: 3 | E9: 330.22 | F9: Store C | G9: Wholesale | H9: 0.15 | I9: Carlos | J9: 842.061 | K9: Cash | M9: 0 | N9: REG100007 | O9: Cust 5301 | P9: 48.01 | Q9: 44935 | R9: 44937 | S9: Cameron | T9: 2023-01
A10: 45581 | B10: South | C10: Chair | D10: 3 | E10: 432.04 | F10: Store D | G10: Wholesale | H10: 0.05 | I10: Bob | J10: 1231.314 | K10: Debit Card | L10: FREESHIP | M10: 1 | N10: REG100008 | O10: Cust 2284 | P10: 42.11 | Q10: 45581 | R10: 45583 | S10: Sophie | T10: 2024-10
A11: 45721 | B11: West | C11: Desk | D11: 5 | E11: 323.28 | F11: Store D | G11: Retail | H11: 0.1 | I11: Frank | J11: 1454.76 | K11: Gift Card | L11: SAVE10 | M11: 0 | N11: REG100009 | O11: Cust 3732 | P11: 41.1 | Q11: 45721 | R11: 45729 | S11: Wendy | T11: 2025-03
A12: 45392 | B12: North | C12: Desk | D12: 15 | E12: 523.29 | F12: Store B | G12: Wholesale | H12: 0.15 | I12: Eva | J12: 6671.9475 | K12: Debit Card | M12: 0 | N12: REG100010 | O12: Cust 1462 | P12: 12.14 | Q12: 45392 | R12: 45399 | S12: Ryan | T12: 2024-04
A13: 45485 | B13: East | C13: Phone | D13: 19 | E13: 207.35 | F13: Store D | G13: Retail | H13: 0.1 | I13: Eva | J13: 3545.685 | K13: Gift Card | M13: 1 | N13: REG100011 | O13: Cust 4330 | P13: 44.89 | Q13: 45485 | R13: 45491 | S13: Eric | T13: 2024-07
A14: 45128 | B14: Central | C14: Phone | D14: 1 | E14: 120.53 | F14: Store B | G14: Retail | H14: 0.05 | I14: Diana | J14: 114.5035 | K14: Cash | L14: WINTER15 | M14: 0 | N14: REG100012 | O14: Cust 2372 | P14: 20.35 | Q14: 45128 | R14: 45138 | S14: Cameron | T14: 2023-07
A15: 45675 | B15: West | C15: Tablet | D15: 1 | E15: 157.83 | F15: Store A | G15: Wholesale | H15: 0.15 | I15: Carlos | J15: 134.1555 | K15: Debit Card | M15: 0 | N15: REG100013 | O15: Cust 4672 | P15: 42.82 | Q15: 45675 | R15: 45679 | S15: Wendy | T15: 2025-01
A16: 45634 | B16: North | C16: Desk | D16: 15 | E16: 220.3 | F16: Store B | G16: Retail | H16: 0.15 | I16: Diana | J16: 2808.825 | K16: Debit Card | M16: 0 | N16: REG100014 | O16: Cust 4548 | P16: 39.66 | Q16: 45634 | R16: 45641 | S16: Ryan | T16: 2024-12
A17: 45788 | B17: West | C17: Chair | D17: 17 | E17: 162.96 | F17: Store A | G17: Wholesale | H17: 0.05 | I17: Eva | J17: 2631.804 | K17: Gift Card | L17: FREESHIP | M17: 0 | N17: REG100015 | O17: Cust 7037 | P17: 8.11 | Q17: 45788 | R17: 45794 | S17: Wendy | T17: 2025-05
A18: 44983 | B18: West | C18: Laptop | D18: 19 | E18: 236.11 | F18: Store D | G18: Wholesale | H18: 0 | I18: Bob | J18: 4486.09 | K18: Online | L18: WINTER15 | M18: 0 | N18: REG100016 | O18: Cust 4975 | P18: 34.11 | Q18: 44983 | R18: 44989 | S18: Wendy | T18: 2023-02
A19: 45440 | B19: Central | C19: Desk | D19: 11 | E19: 573.14 | F19: Store D | G19: Retail | H19: 0.05 | I19: Diana | J19: 5989.313 | K19: Cash | L19: SAVE10 | M19: 0 | N19: REG100017 | O19: Cust 8014 | P19: 34.71 | Q19: 45440 | R19: 45444 | S19: Cameron | T19: 2024-05
A20: 45260 | B20: East | C20: Phone | D20: 20 | E20: 519.04 | F20: Store B | G20: Retail | H20: 0.15 | I20: Carlos | J20: 8823.68 | K20: Gift Card | L20: FREESHIP | M20: 0 | N20: REG100018 | O20: Cust 1228 | P20: 19.43 | Q20: 45260 | R20: 45268 | S20: Eric | T20: 2023-11
A21: 45099 | B21: West | C21: Desk | D21: 14 | E21: 30.83 | F21: Store B | G21: Retail | H21: 0 | I21: Carlos | J21: 431.62 | K21: Online | L21: WINTER15 | M21: 1 | N21: REG100019 | O21: Cust 4247 | P21: 7.1 | Q21: 45099 | R21: 45109 | S21: Wendy | T21: 2023-06
A22: 45813 | B22: West | C22: Phone | D22: 10 | E22: 319.05 | F22: Store D | G22: Wholesale | H22: 0 | I22: Diana | J22: 3190.5 | K22: Online | M22: 0 | N22: REG100020 | O22: Cust 4199 | P22: 28.43 | Q22: 45813 | R22: 45816 | S22: Wendy | T22: 2025-06
A23: 44988 | B23: Central | C23: Chair | D23: 14 | E23: 312.79 | F23: Store A | G23: Retail | H23: 0.05 | I23: Bob | J23: 4160.107 | K23: Online | M23: 1 | N23: REG100021 | O23: Cust 4186 | P23: 46.83 | Q23: 44988 | R23: 44993 | S23: Cameron | T23: 2023-03
A24: 45340 | B24: North | C24: Laptop | D24: 14 | E24: 395.45 | F24: Store C | G24: Retail | H24: 0 | I24: Carlos | J24: 5536.3 | K24: Cash | L24: FREESHIP | M24: 1 | N24: REG100022 | O24: Cust 8137 | P24: 36.45 | Q24: 45340 | R24: 45344 | S24: Ryan | T24: 2024-02
A25: 45144 | B25: Central | C25: Laptop | D25: 12 | E25: 472.72 | F25: Store D | G25: Retail | H25: 0.15 | I25: Diana | J25: 4821.744 | K25: Credit Card | M25: 0 | N25: REG100023 | O25: Cust 4638 | P25: 27.97 | Q25: 45144 | R25: 45152 | S25: Cameron | T25: 2023-08
A26: 45435 | B26: North | C26: Desk | D26: 5 | E26: 288.01 | F26: Store A | G26: Wholesale | H26: 0 | I26: Eva | J26: 1440.05 | K26: Credit Card | L26: FREESHIP | M26: 0 | N26: REG100024 | O26: Cust 8538 | P26: 46.69 | Q26: 45435 | R26: 45442 | S26: Ryan | T26: 2024-05
A27: 45222 | B27: East | C27: Phone | D27: 13 | E27: 562.29 | F27: Store D | G27: Retail | H27: 0 | I27: Diana | J27: 7309.77 | K27: Gift Card | L27: SAVE10 | M27: 0 | N27: REG100025 | O27: Cust 6322 | P27: 38.13 | Q27: 45222 | R27: 45227 | S27: Eric | T27: 2023-10
A28: 45824 | B28: West | C28: Phone | D28: 1 | E28: 101.73 | F28: Store D | G28: Retail | H28: 0 | I28: Frank | J28: 101.73 | K28: Debit Card | L28: WINTER15 | M28: 0 | N28: REG100026 | O28: Cust 2609 | P28: 11.59 | Q28: 45824 | R28: 45833 | S28: Wendy | T28: 2025-06
A29: 44988 | B29: North | C29: Phone | D29: 4 | E29: 279.49 | F29: Store B | G29: Retail | H29: 0 | I29: Diana | J29: 1117.96 | K29: Credit Card | L29: FREESHIP | M29: 0 | N29: REG100027 | O29: Cust 6880 | P29: 24.78 | Q29: 44988 | R29: 44993 | S29: Ryan | T29: 2023-03
A30: 45614 | B30: South | C30: Laptop | D30: 1 | E30: 178.55 | F30: Store A | G30: Retail | H30: 0.15 | I30: Carlos | J30: 151.7675 | K30: Debit Card | L30: SAVE10 | M30: 1 | N30: REG100028 | O30: Cust 1997 | P30: 7.61 | Q30: 45614 | R30: 45617 | S30: Sophie | T30: 2024-11
A31: 45055 | B31: Central | C31: Tablet | D31: 1 | E31: 472.07 | F31: Store A | G31: Wholesale | H31: 0.1 | I31: Carlos | J31: 424.863 | K31: Online | L31: FREESHIP | M31: 0 | N31: REG100029 | O31: Cust 7072 | P31: 33.17 | Q31: 45055 | R31: 45063 | S31: Cameron | T31: 2023-05
A32: 45633 | B32: North | C32: Tablet | D32: 12 | E32: 306.29 | F32: Store D | G32: Retail | H32: 0 | I32: Frank | J32: 3675.48 | K32: Debit Card | L32: SAVE10 | M32: 0 | N32: REG100030 | O32: Cust 7201 | P32: 37.38 | Q32: 45633 | R32: 45640 | S32: Ryan | T32: 2024-12
A33: 45335 | B33: North | C33: Phone | D33: 7 | E33: 434.77 | F33: Store C | G33: Retail | H33: 0.15 | I33: Frank | J33: 2586.8815 | K33: Online | L33: SAVE10 | M33: 0 | N33: REG100031 | O33: Cust 9923 | P33: 12.35 | Q33: 45335 | R33: 45337 | S33: Ryan | T33: 2024-02
A34: 45725 | B34: South | C34: Desk | D34: 6 | E34: 64.98 | F34: Store C | G34: Retail | H34: 0 | I34: Carlos | J34: 389.88 | K34: Debit Card | L34: WINTER15 | M34: 0 | N34: REG100032 | O34: Cust 2205 | P34: 21.25 | Q34: 45725 | R34: 45731 | S34: Sophie | T34: 2025-03
A35: 45021 | B35: Central | C35: Desk | D35: 17 | E35: 476.49 | F35: Store D | G35: Retail | H35: 0 | I35: Alice | J35: 8100.33 | K35: Gift Card | M35: 0 | N35: REG100033 | O35: Cust 6403 | P35: 17.91 | Q35: 45021 | R35: 45027 | S35: Cameron | T35: 2023-04
A36: 45785 | B36: North | C36: Monitor | D36: 4 | E36: 559.72 | F36: Store D | G36: Retail | H36: 0.15 | I36: Diana | J36: 1903.048 | K36: Online | L36: SAVE10 | M36: 0 | N36: REG100034 | O36: Cust 3953 | P36: 41.91 | Q36: 45785 | R36: 45789 | S36: Ryan | T36: 2025-05
A37: 45172 | B37: North | C37: Tablet | D37: 14 | E37: 82.14 | F37: Store C | G37: Retail | H37: 0 | I37: Alice | J37: 1149.96 | K37: Credit Card | M37: 0 | N37: REG100035 | O37: Cust 7902 | P37: 12.57 | Q37: 45172 | R37: 45180 | S37: Ryan | T37: 2023-09
A38: 45737 | B38: Central | C38: Chair | D38: 9 | E38: 343.21 | F38: Store A | G38: Retail | H38: 0.05 | I38: Carlos | J38: 2934.4455 | K38: Debit Card | L38: FREESHIP | M38: 0 | N38: REG100036 | O38: Cust 9968 | P38: 40.29 | Q38: 45737 | R38: 45744 | S38: Cameron | T38: 2025-03
A39: 45828 | B39: South | C39: Chair | D39: 7 | E39: 301.01 | F39: Store B | G39: Retail | H39: 0.15 | I39: Diana | J39: 1791.0095 | K39: Cash | L39: SAVE10 | M39: 1 | N39: REG100037 | O39: Cust 3787 | P39: 34.97 | Q39: 45828 | R39: 45838 | S39: Sophie | T39: 2025-06
A40: 45337 | B40: Central | C40: Printer | D40: 14 | E40: 428.13 | F40: Store C | G40: Retail | H40: 0.1 | I40: Bob | J40: 5394.438 | K40: Cash | M40: 1 | N40: REG100038 | O40: Cust 2469 | P40: 24.77 | Q40: 45337 | R40: 45347 | S40: Cameron | T40: 2024-02
A41: 45086 | B41: Central | C41: Laptop | D41: 2 | E41: 503.28 | F41: Store D | G41: Retail | H41: 0.15 | I41: Alice | J41: 855.576 | K41: Gift Card | M41: 0 | N41: REG100039 | O41: Cust 6468 | P41: 34.79 | Q41: 45086 | R41: 45094 | S41: Cameron | T41: 2023-06
A42: 45148 | B42: South | C42: Printer | D42: 5 | E42: 470.32 | F42: Store A | G42: Retail | H42: 0.1 | I42: Eva | J42: 2116.44 | K42: Debit Card | L42: SAVE10 | M42: 0 | N42: REG100040 | O42: Cust 5312 | P42: 17.77 | Q42: 45148 | R42: 45152 | S42: Sophie | T42: 2023-08
A43: 45459 | B43: Central | C43: Printer | D43: 20 | E43: 65.17 | F43: Store C | G43: Wholesale | H43: 0.05 | I43: Eva | J43: 1238.23 | K43: Gift Card | L43: FREESHIP | M43: 0 | N43: REG100041 | O43: Cust 1482 | P43: 21.72 | Q43: 45459 | R43: 45468 | S43: Cameron | T43: 2024-06
A44: 45130 | B44: South | C44: Laptop | D44: 12 | E44: 36.17 | F44: Store A | G44: Retail | H44: 0 | I44: Eva | J44: 434.04 | K44: Online | L44: WINTER15 | M44: 0 | N44: REG100042 | O44: Cust 7903 | P44: 34.85 | Q44: 45130 | R44: 45133 | S44: Sophie | T44: 2023-07
A45: 45066 | B45: Central | C45: Printer | D45: 4 | E45: 459.31 | F45: Store D | G45: Wholesale | H45: 0.15 | I45: Carlos | J45: 1561.654 | K45: Gift Card | L45: WINTER15 | M45: 1 | N45: REG100043 | O45: Cust 9605 | P45: 27.39 | Q45: 45066 | R45: 45073 | S45: Cameron | T45: 2023-05
A46: 45107 | B46: South | C46: Laptop | D46: 2 | E46: 416.06 | F46: Store D | G46: Retail | H46: 0.05 | I46: Eva | J46: 790.514 | K46: Debit Card | L46: SAVE10 | M46: 0 | N46: REG100044 | O46: Cust 3298 | P46: 11.62 | Q46: 45107 | R46: 45111 | S46: Sophie | T46: 2023-06
A47: 45447 | B47: South | C47: Tablet | D47: 16 | E47: 302.58 | F47: Store D | G47: Retail | H47: 0 | I47: Alice | J47: 4841.28 | K47: Online | L47: WINTER15 | M47: 1 | N47: REG100045 | O47: Cust 5533 | P47: 20.76 | Q47: 45447 | R47: 45457 | S47: Sophie | T47: 2024-06
A48: 45691 | B48: West | C48: Chair | D48: 11 | E48: 33.13 | F48: Store A | G48: Retail | H48: 0.15 | I48: Frank | J48: 309.7655 | K48: Online | L48: FREESHIP | M48: 0 | N48: REG100046 | O48: Cust 6362 | P48: 24.95 | Q48: 45691 | R48: 45693 | S48: Wendy | T48: 2025-02
A49: 45300 | B49: East | C49: Tablet | D49: 8 | E49: 582.52 | F49: Store D | G49: Retail | H49: 0.15 | I49: Frank | J49: 3961.136 | K49: Gift Card | L49: WINTER15 | M49: 0 | N49: REG100047 | O49: Cust 4826 | P49: 6.47 | Q49: 45300 | R49: 45304 | S49: Eric | T49: 2024-01
A50: 45365 | B50: North | C50: Desk | D50: 5 | E50: 165.15 | F50: Store A | G50: Retail | H50: 0.1 | I50: Eva | J50: 743.175 | K50: Gift Card | M50: 0 | N50: REG100048 | O50: Cust 2171 | P50: 20.57 | Q50: 45365 | R50: 45367 | S50: Ryan | T50: 2024-03
A51: 45541 | B51: West | C51: Monitor | D51: 14 | E51: 242.82 | F51: Store D | G51: Wholesale | H51: 0.15 | I51: Alice | J51: 2889.558 | K51: Cash | L51: WINTER15 | M51: 1 | N51: REG100049 | O51: Cust 4005 | P51: 20.71 | Q51: 45541 | R51: 45548 | S51: Wendy | T51: 2024-09
A52: 45002 | B52: East | C52: Monitor | D52: 13 | E52: 65.99 | F52: Store A | G52: Wholesale | H52: 0.1 | I52: Frank | J52: 772.083 | K52: Cash | L52: WINTER15 | M52: 0 | N52: REG100050 | O52: Cust 7032 | P52: 12.87 | Q52: 45002 | R52: 45005 | S52: Eric | T52: 2023-03
A53: 45674 | B53: West | C53: Chair | D53: 2 | E53: 251.69 | F53: Store C | G53: Wholesale | H53: 0 | I53: Alice | J53: 503.38 | K53: Debit Card | L53: FREESHIP | M53: 0 | N53: REG100051 | O53: Cust 7167 | P53: 42.49 | Q53: 45674 | R53: 45681 | S53: Wendy | T53: 2025-01
A54: 45547 | B54: South | C54: Laptop | D54: 1 | E54: 269.41 | F54: Store B | G54: Wholesale | H54: 0.1 | I54: Eva | J54: 242.469 | K54: Cash | L54: WINTER15 | M54: 1 | N54: REG100052 | O54: Cust 5702 | P54: 19.22 | Q54: 45547 | R54: 45553 | S54: Sophie | T54: 2024-09
A55: 45296 | B55: South | C55: Monitor | D55: 2 | E55: 371.3 | F55: Store B | G55: Wholesale | H55: 0.05 | I55: Bob | J55: 705.47 | K55: Credit Card | L55: SAVE10 | M55: 0 | N55: REG100053 | O55: Cust 4944 | P55: 36.51 | Q55: 45296 | R55: 45306 | S55: Sophie | T55: 2024-01
A56: 45401 | B56: West | C56: Tablet | D56: 11 | E56: 288.24 | F56: Store A | G56: Wholesale | H56: 0.15 | I56: Diana | J56: 2695.044 | K56: Online | M56: 0 | N56: REG100054 | O56: Cust 8149 | P56: 37.39 | Q56: 45401 | R56: 45407 | S56: Wendy | T56: 2024-04
A57: 45819 | B57: Central | C57: Tablet | D57: 11 | E57: 232.75 | F57: Store D | G57: Wholesale | H57: 0.05 | I57: Eva | J57: 2432.2375 | K57: Credit Card | L57: SAVE10 | M57: 0 | N57: REG100055 | O57: Cust 3638 | P57: 36.33 | Q57: 45819 | R57: 45829 | S57: Cameron | T57: 2025-06
A58: 45722 | B58: East | C58: Phone | D58: 17 | E58: 146.28 | F58: Store B | G58: Retail | H58: 0.15 | I58: Carlos | J58: 2113.746 | K58: Cash | L58: SAVE10 | M58: 0 | N58: REG100056 | O58: Cust 9973 | P58: 7.84 | Q58: 45722 | R58: 45731 | S58: Eric | T58: 2025-03
A59: 45070 | B59: East | C59: Chair | D59: 5 | E59: 100.38 | F59: Store C | G59: Retail | H59: 0.1 | I59: Eva | J59: 451.71 | K59: Gift Card | L59: WINTER15 | M59: 1 | N59: REG100057 | O59: Cust 4214 | P59: 18.35 | Q59: 45070 | R59: 45072 | S59: Eric | T59: 2023-05
A60: 44953 | B60: South | C60: Phone | D60: 11 | E60: 375.48 | F60: Store B | G60: Retail | H60: 0.05 | I60: Bob | J60: 3923.766 | K60: Debit Card | L60: WINTER15 | M60: 0 | N60: REG100058 | O60: Cust 2647 | P60: 15.95 | Q60: 44953 | R60: 44960 | S60: Sophie | T60: 2023-01
A61: 45372 | B61: South | C61: Laptop | D61: 18 | E61: 316.89 | F61: Store B | G61: Wholesale | H61: 0.05 | I61: Bob | J61: 5418.819 | K61: Cash | L61: FREESHIP | M61: 0 | N61: REG100059 | O61: Cust 3552 | P61: 15.69 | Q61: 45372 | R61: 45378 | S61: Sophie | T61: 2024-03
A62: 45682 | B62: West | C62: Laptop | D62: 20 | E62: 295.06 | F62: Store D | G62: Retail | H62: 0.15 | I62: Frank | J62: 5016.02 | K62: Online | L62: SAVE10 | M62: 1 | N62: REG100060 | O62: Cust 3354 | P62: 13.66 | Q62: 45682 | R62: 45688 | S62: Wendy | T62: 2025-01
A63: 45089 | B63: Central | C63: Phone | D63: 8 | E63: 301.68 | F63: Store D | G63: Retail | H63: 0 | I63: Eva | J63: 2413.44 | K63: Cash | L63: SAVE10 | M63: 0 | N63: REG100061 | O63: Cust 3903 | P63: 36.54 | Q63: 45089 | R63: 45098 | S63: Cameron | T63: 2023-06
A64: 45738 | B64: Central | C64: Chair | D64: 3 | E64: 475.39 | F64: Store B | G64: Retail | H64: 0.1 | I64: Alice | J64: 1283.553 | K64: Gift Card | M64: 0 | N64: REG100062 | O64: Cust 5358 | P64: 15.62 | Q64: 45738 | R64: 45742 | S64: Cameron | T64: 2025-03
A65: 45346 | B65: Central | C65: Desk | D65: 16 | E65: 47.25 | F65: Store D | G65: Retail | H65: 0.15 | I65: Bob | J65: 642.6 | K65: Debit Card | L65: FREESHIP | M65: 0 | N65: REG100063 | O65: Cust 8144 | P65: 29.5 | Q65: 45346 | R65: 45349 | S65: Cameron | T65: 2024-02
A66: 45269 | B66: South | C66: Chair | D66: 15 | E66: 511.17 | F66: Store B | G66: Wholesale | H66: 0 | I66: Frank | J66: 7667.55 | K66: Online | L66: FREESHIP | M66: 0 | N66: REG100064 | O66: Cust 6747 | P66: 21.77 | Q66: 45269 | R66: 45272 | S66: Sophie | T66: 2023-12
A67: 45200 | B67: Central | C67: Monitor | D67: 3 | E67: 66.58 | F67: Store B | G67: Retail | H67: 0.1 | I67: Frank | J67: 179.766 | K67: Debit Card | L67: FREESHIP | M67: 0 | N67: REG100065 | O67: Cust 8330 | P67: 22.43 | Q67: 45200 | R67: 45204 | S67: Cameron | T67: 2023-10
A68: 45138 | B68: West | C68: Tablet | D68: 5 | E68: 490.52 | F68: Store D | G68: Wholesale | H68: 0.05 | I68: Frank | J68: 2329.97 | K68: Online | M68: 0 | N68: REG100066 | O68: Cust 7186 | P68: 12.24 | Q68: 45138 | R68: 45145 | S68: Wendy | T68: 2023-07
A69: 45650 | B69: South | C69: Chair | D69: 8 | E69: 405.96 | F69: Store A | G69: Wholesale | H69: 0.05 | I69: Carlos | J69: 3085.296 | K69: Credit Card | L69: WINTER15 | M69: 0 | N69: REG100067 | O69: Cust 8287 | P69: 41.27 | Q69: 45650 | R69: 45657 | S69: Sophie | T69: 2024-12
A70: 45611 | B70: North | C70: Phone | D70: 1 | E70: 159.41 | F70: Store B | G70: Retail | H70: 0.1 | I70: Bob | J70: 143.469 | K70: Credit Card | L70: FREESHIP | M70: 0 | N70: REG100068 | O70: Cust 3986 | P70: 35.14 | Q70: 45611 | R70: 45615 | S70: Ryan | T70: 2024-11
A71: 45729 | B71: West | C71: Monitor | D71: 16 | E71: 38.49 | F71: Store C | G71: Retail | H71: 0.15 | I71: Carlos | J71: 523.464 | K71: Debit Card | L71: SAVE10 | M71: 0 | N71: REG100069 | O71: Cust 3213 | P71: 8.38 | Q71: 45729 | R71: 45738 | S71: Wendy | T71: 2025-03
A72: 45354 | B72: East | C72: Tablet | D72: 15 | E72: 328.36 | F72: Store D | G72: Retail | H72: 0.15 | I72: Alice | J72: 4186.59 | K72: Gift Card | L72: WINTER15 | M72: 0 | N72: REG100070 | O72: Cust 1907 | P72: 15.76 | Q72: 45354 | R72: 45363 | S72: Eric | T72: 2024-03
A73: 44968 | B73: Central | C73: Tablet | D73: 20 | E73: 548.01 | F73: Store A | G73: Wholesale | H73: 0.1 | I73: Eva | J73: 9864.18 | K73: Credit Card | L73: WINTER15 | M73: 1 | N73: REG100071 | O73: Cust 4639 | P73: 5.89 | Q73: 44968 | R73: 44971 | S73: Cameron | T73: 2023-02
A74: 45225 | B74: South | C74: Desk | D74: 13 | E74: 484.45 | F74: Store B | G74: Wholesale | H74: 0.05 | I74: Carlos | J74: 5982.9575 | K74: Gift Card | L74: WINTER15 | M74: 1 | N74: REG100072 | O74: Cust 4153 | P74: 6.57 | Q74: 45225 | R74: 45235 | S74: Sophie | T74: 2023-10
A75: 45220 | B75: South | C75: Monitor | D75: 13 | E75: 195.84 | F75: Store A | G75: Wholesale | H75: 0.05 | I75: Alice | J75: 2418.624 | K75: Credit Card | M75: 0 | N75: REG100073 | O75: Cust 7096 | P75: 33.52 | Q75: 45220 | R75: 45227 | S75: Sophie | T75: 2023-10
A76: 45305 | B76: Central | C76: Tablet | D76: 19 | E76: 29.94 | F76: Store D | G76: Retail | H76: 0.15 | I76: Diana | J76: 483.531 | K76: Debit Card | L76: FREESHIP | M76: 0 | N76: REG100074 | O76: Cust 3806 | P76: 33.59 | Q76: 45305 | R76: 45311 | S76: Cameron | T76: 2024-01
A77: 45134 | B77: Central | C77: Desk | D77: 10 | E77: 553.91 | F77: Store D | G77: Wholesale | H77: 0.1 | I77: Eva | J77: 4985.19 | K77: Online | M77: 0 | N77: REG100075 | O77: Cust 9345 | P77: 31.3 | Q77: 45134 | R77: 45138 | S77: Cameron | T77: 2023-07
A78: 45588 | B78: South | C78: Phone | D78: 14 | E78: 445.52 | F78: Store B | G78: Retail | H78: 0.1 | I78: Bob | J78: 5613.552 | K78: Online | L78: SAVE10 | M78: 0 | N78: REG100076 | O78: Cust 4456 | P78: 14.41 | Q78: 45588 | R78: 45590 | S78: Sophie | T78: 2024-10
A79: 45195 | B79: South | C79: Chair | D79: 5 | E79: 551.58 | F79: Store B | G79: Retail | H79: 0.15 | I79: Alice | J79: 2344.215 | K79: Online | L79: WINTER15 | M79: 1 | N79: REG100077 | O79: Cust 1089 | P79: 7.87 | Q79: 45195 | R79: 45200 | S79: Sophie | T79: 2023-09
A80: 45276 | B80: East | C80: Phone | D80: 13 | E80: 241.4 | F80: Store D | G80: Retail | H80: 0 | I80: Carlos | J80: 3138.2 | K80: Gift Card | L80: SAVE10 | M80: 0 | N80: REG100078 | O80: Cust 7230 | P80: 49.05 | Q80: 45276 | R80: 45280 | S80: Eric | T80: 2023-12
A81: 45293 | B81: Central | C81: Printer | D81: 19 | E81: 351.93 | F81: Store A | G81: Wholesale | H81: 0 | I81: Alice | J81: 6686.67 | K81: Credit Card | M81: 0 | N81: REG100079 | O81: Cust 6597 | P81: 39.98 | Q81: 45293 | R81: 45296 | S81: Cameron | T81: 2024-01
A82: 45338 | B82: North | C82: Phone | D82: 4 | E82: 83.75 | F82: Store A | G82: Retail | H82: 0.05 | I82: Alice | J82: 318.25 | K82: Debit Card | L82: SAVE10 | M82: 1 | N82: REG100080 | O82: Cust 4108 | P82: 38.82 | Q82: 45338 | R82: 45347 | S82: Ryan | T82: 2024-02
A83: 45415 | B83: East | C83: Monitor | D83: 5 | E83: 416.95 | F83: Store A | G83: Wholesale | H83: 0.15 | I83: Frank | J83: 1772.0375 | K83: Online | M83: 1 | N83: REG100081 | O83: Cust 2883 | P83: 24.03 | Q83: 45415 | R83: 45424 | S83: Eric | T83: 2024-05
A84: 45073 | B84: West | C84: Monitor | D84: 18 | E84: 142.43 | F84: Store C | G84: Retail | H84: 0.05 | I84: Bob | J84: 2435.553 | K84: Credit Card | L84: SAVE10 | M84: 1 | N84: REG100082 | O84: Cust 5018 | P84: 12.38 | Q84: 45073 | R84: 45079 | S84: Wendy | T84: 2023-05
A85: 44931 | B85: East | C85: Desk | D85: 12 | E85: 582.52 | F85: Store A | G85: Wholesale | H85: 0 | I85: Bob | J85: 6990.24 | K85: Credit Card | L85: FREESHIP | M85: 0 | N85: REG100083 | O85: Cust 1231 | P85: 41.16 | Q85: 44931 | R85: 44937 | S85: Eric | T85: 2023-01
A86: 45798 | B86: East | C86: Chair | D86: 20 | E86: 129.56 | F86: Store A | G86: Retail | H86: 0.15 | I86: Diana | J86: 2202.52 | K86: Online | L86: WINTER15 | M86: 0 | N86: REG100084 | O86: Cust 2209 | P86: 40.21 | Q86: 45798 | R86: 45800 | S86: Eric | T86: 2025-05
A87: 45128 | B87: Central | C87: Tablet | D87: 17 | E87: 431.82 | F87: Store B | G87: Retail | H87: 0 | I87: Eva | J87: 7340.94 | K87: Gift Card | L87: FREESHIP | M87: 1 | N87: REG100085 | O87: Cust 6684 | P87: 37.75 | Q87: 45128 | R87: 45132 | S87: Cameron | T87: 2023-07
A88: 45802 | B88: East | C88: Laptop | D88: 15 | E88: 15.85 | F88: Store C | G88: Retail | H88: 0 | I88: Bob | J88: 237.75 | K88: Debit Card | L88: WINTER15 | M88: 0 | N88: REG100086 | O88: Cust 5289 | P88: 23.49 | Q88: 45802 | R88: 45811 | S88: Eric | T88: 2025-05
A89: 45612 | B89: South | C89: Tablet | D89: 20 | E89: 548.34 | F89: Store B | G89: Retail | H89: 0.1 | I89: Bob | J89: 9870.12 | K89: Gift Card | L89: WINTER15 | M89: 0 | N89: REG100087 | O89: Cust 9159 | P89: 33.47 | Q89: 45612 | R89: 45618 | S89: Sophie | T89: 2024-11
A90: 45249 | B90: North | C90: Laptop | D90: 16 | E90: 525.83 | F90: Store C | G90: Wholesale | H90: 0.05 | I90: Frank | J90: 7992.616 | K90: Online | M90: 0 | N90: REG100088 | O90: Cust 4844 | P90: 36.47 | Q90: 45249 | R90: 45255 | S90: Ryan | T90: 2023-11
A91: 45669 | B91: Central | C91: Laptop | D91: 15 | E91: 411.38 | F91: Store A | G91: Wholesale | H91: 0.05 | I91: Bob | J91: 5862.165 | K91: Online | L91: SAVE10 | M91: 0 | N91: REG100089 | O91: Cust 3273 | P91: 48.51 | Q91: 45669 | R91: 45678 | S91: Cameron | T91: 2025-01
A92: 45014 | B92: North | C92: Monitor | D92: 19 | E92: 559.95 | F92: Store A | G92: Wholesale | H92: 0.1 | I92: Carlos | J92: 9575.145 | K92: Credit Card | L92: WINTER15 | M92: 0 | N92: REG100090 | O92: Cust 8160 | P92: 18.3 | Q92: 45014 | R92: 45019 | S92: Ryan | T92: 2023-03
A93: 45717 | B93: North | C93: Desk | D93: 8 | E93: 179.9 | F93: Store C | G93: Retail | H93: 0.05 | I93: Carlos | J93: 1367.24 | K93: Online | L93: SAVE10 | M93: 0 | N93: REG100091 | O93: Cust 4439 | P93: 14.8 | Q93: 45717 | R93: 45721 | S93: Ryan | T93: 2025-03
A94: 45217 | B94: North | C94: Chair | D94: 12 | E94: 494.15 | F94: Store B | G94: Wholesale | H94: 0.15 | I94: Diana | J94: 5040.33 | K94: Online | L94: SAVE10 | M94: 1 | N94: REG100092 | O94: Cust 1127 | P94: 18.05 | Q94: 45217 | R94: 45219 | S94: Ryan | T94: 2023-10
A95: 45760 | B95: East | C95: Desk | D95: 10 | E95: 462.99 | F95: Store C | G95: Wholesale | H95: 0 | I95: Bob | J95: 4629.9 | K95: Credit Card | L95: WINTER15 | M95: 0 | N95: REG100093 | O95: Cust 4696 | P95: 5.01 | Q95: 45760 | R95: 45762 | S95: Eric | T95: 2025-04
A96: 45790 | B96: Central | C96: Laptop | D96: 7 | E96: 460.24 | F96: Store A | G96: Retail | H96: 0.05 | I96: Alice | J96: 3060.596 | K96: Cash | L96: SAVE10 | M96: 1 | N96: REG100094 | O96: Cust 3014 | P96: 11.54 | Q96: 45790 | R96: 45800 | S96: Cameron | T96: 2025-05
A97: 45403 | B97: West | C97: Printer | D97: 17 | E97: 309.52 | F97: Store B | G97: Wholesale | H97: 0.05 | I97: Eva | J97: 4998.748 | K97: Online | L97: FREESHIP | M97: 0 | N97: REG100095 | O97: Cust 2539 | P97: 6.11 | Q97: 45403 | R97: 45409 | S97: Wendy | T97: 2024-04
A98: 45688 | B98: Central | C98: Monitor | D98: 1 | E98: 323.83 | F98: Store B | G98: Wholesale | H98: 0.05 | I98: Eva | J98: 307.6385 | K98: Credit Card | L98: WINTER15 | M98: 0 | N98: REG100096 | O98: Cust 3916 | P98: 27.48 | Q98: 45688 | R98: 45696 | S98: Cameron | T98: 2025-01
A99: 45730 | B99: Central | C99: Chair | D99: 10 | E99: 503.07 | F99: Store C | G99: Retail | H99: 0 | I99: Bob | J99: 5030.7 | K99: Credit Card | L99: FREESHIP | M99: 0 | N99: REG100097 | O99: Cust 6329 | P99: 44.61 | Q99: 45730 | R99: 45735 | S99: Cameron | T99: 2025-03
A100: 45438 | B100: West | C100: Laptop | D100: 20 | E100: 491.68 | F100: Store D | G100: Wholesale | H100: 0.15 | I100: Alice | J100: 8358.56 | K100: Online | L100: SAVE10 | M100: 1 | N100: REG100098 | O100: Cust 4384 | P100: 43.46 | Q100: 45438 | R100: 45441 | S100: Wendy | T100: 2024-05
...

Sheet Analytics
A1: 1. Sales by Region - X=Region Y=SUM(TotalPrice) | D1: 2. Product X=Product Y=Sales | G1: 3. Customer X=Type Y=Qty | J1: 4. Payment X=Payment Y=Sales
A2: Region | B2: Total Sales | D2: Product | E2: Sales | G2: CustomerType | H2: Qty | J2: Payment | K2: Sales
A3: Central | B3: =SUMIF(Data!$B$2:$B$1501,"Central",Data!$J$2:$J$1501) | D3: Chair | E3: =SUMIF(Data!$C$2:$C$1501,"Chair",Data!$J$2:$J$1501) | G3: Retail | H3: =SUMIF(Data!$G$2:$G$1501,"Retail",Data!$D$2:$D$1501) | J3: Cash | K3: =SUMIF(Data!$K$2:$K$1501,"Cash",Data!$J$2:$J$1501)
A4: East | B4: =SUMIF(Data!$B$2:$B$1501,"East",Data!$J$2:$J$1501) | D4: Desk | E4: =SUMIF(Data!$C$2:$C$1501,"Desk",Data!$J$2:$J$1501) | G4: Wholesale | H4: =SUMIF(Data!$G$2:$G$1501,"Wholesale",Data!$D$2:$D$1501) | J4: Credit Card | K4: =SUMIF(Data!$K$2:$K$1501,"Credit Card",Data!$J$2:$J$1501)
A5: North | B5: =SUMIF(Data!$B$2:$B$1501,"North",Data!$J$2:$J$1501) | D5: Laptop | E5: =SUMIF(Data!$C$2:$C$1501,"Laptop",Data!$J$2:$J$1501) | J5: Debit Card | K5: =SUMIF(Data!$K$2:$K$1501,"Debit Card",Data!$J$2:$J$1501)
A6: South | B6: =SUMIF(Data!$B$2:$B$1501,"South",Data!$J$2:$J$1501) | D6: Monitor | E6: =SUMIF(Data!$C$2:$C$1501,"Monitor",Data!$J$2:$J$1501) | J6: Gift Card | K6: =SUMIF(Data!$K$2:$K$1501,"Gift Card",Data!$J$2:$J$1501)
A7: West | B7: =SUMIF(Data!$B$2:$B$1501,"West",Data!$J$2:$J$1501) | D7: Phone | E7: =SUMIF(Data!$C$2:$C$1501,"Phone",Data!$J$2:$J$1501) | J7: Online | K7: =SUMIF(Data!$K$2:$K$1501,"Online",Data!$J$2:$J$1501)
D8: Printer | E8: =SUMIF(Data!$C$2:$C$1501,"Printer",Data!$J$2:$J$1501)
D9: Tablet | E9: =SUMIF(Data!$C$2:$C$1501,"Tablet",Data!$J$2:$J$1501)
A12: 5. Store X=Store Y=Sales | D12: 6. Salesperson X=Salesperson Y=Sales | G12: 7. Monthly Sales X=YearMonth Y=Sales | L12: 8. Promo X=Promo Y=Sales
A13: Store | B13: Sales | D13: Salesperson | E13: Sales | G13: YearMonth | H13: Sales | I13: Qty | J13: Cumulative | L13: Promotion | M13: Sales | N13: Avg Discount
A14: Store A | B14: =SUMIF(Data!$F$2:$F$1501,"Store A",Data!$J$2:$J$1501) | D14: Alice | E14: =SUMIF(Data!$I$2:$I$1501,"Alice",Data!$J$2:$J$1501) | G14: 2023-01 | H14: =SUMIF(Data!$T$2:$T$1501,"2023-01",Data!$J$2:$J$1501) | I14: =SUMIF(Data!$T$2:$T$1501,"2023-01",Data!$D$2:$D$1501) | J14: =SUM($H$14:H14) | L14: FREESHIP | M14: =SUMIF(Data!$L$2:$L$1501,"FREESHIP",Data!$J$2:$J$1501) | N14: =AVERAGEIF(Data!$L$2:$L$1501,"FREESHIP",Data!$H$2:$H$1501)
A15: Store B | B15: =SUMIF(Data!$F$2:$F$1501,"Store B",Data!$J$2:$J$1501) | D15: Bob | E15: =SUMIF(Data!$I$2:$I$1501,"Bob",Data!$J$2:$J$1501) | G15: 2023-02 | H15: =SUMIF(Data!$T$2:$T$1501,"2023-02",Data!$J$2:$J$1501) | I15: =SUMIF(Data!$T$2:$T$1501,"2023-02",Data!$D$2:$D$1501) | J15: =SUM($H$14:H15) | L15: SAVE10 | M15: =SUMIF(Data!$L$2:$L$1501,"SAVE10",Data!$J$2:$J$1501) | N15: =AVERAGEIF(Data!$L$2:$L$1501,"SAVE10",Data!$H$2:$H$1501)
A16: Store C | B16: =SUMIF(Data!$F$2:$F$1501,"Store C",Data!$J$2:$J$1501) | D16: Carlos | E16: =SUMIF(Data!$I$2:$I$1501,"Carlos",Data!$J$2:$J$1501) | G16: 2023-03 | H16: =SUMIF(Data!$T$2:$T$1501,"2023-03",Data!$J$2:$J$1501) | I16: =SUMIF(Data!$T$2:$T$1501,"2023-03",Data!$D$2:$D$1501) | J16: =SUM($H$14:H16) | L16: WINTER15 | M16: =SUMIF(Data!$L$2:$L$1501,"WINTER15",Data!$J$2:$J$1501) | N16: =AVERAGEIF(Data!$L$2:$L$1501,"WINTER15",Data!$H$2:$H$1501)
A17: Store D | B17: =SUMIF(Data!$F$2:$F$1501,"Store D",Data!$J$2:$J$1501) | D17: Diana | E17: =SUMIF(Data!$I$2:$I$1501,"Diana",Data!$J$2:$J$1501) | G17: 2023-04 | H17: =SUMIF(Data!$T$2:$T$1501,"2023-04",Data!$J$2:$J$1501) | I17: =SUMIF(Data!$T$2:$T$1501,"2023-04",Data!$D$2:$D$1501) | J17: =SUM($H$14:H17)
D18: Eva | E18: =SUMIF(Data!$I$2:$I$1501,"Eva",Data!$J$2:$J$1501) | G18: 2023-05 | H18: =SUMIF(Data!$T$2:$T$1501,"2023-05",Data!$J$2:$J$1501) | I18: =SUMIF(Data!$T$2:$T$1501,"2023-05",Data!$D$2:$D$1501) | J18: =SUM($H$14:H18)
D19: Frank | E19: =SUMIF(Data!$I$2:$I$1501,"Frank",Data!$J$2:$J$1501) | G19: 2023-06 | H19: =SUMIF(Data!$T$2:$T$1501,"2023-06",Data!$J$2:$J$1501) | I19: =SUMIF(Data!$T$2:$T$1501,"2023-06",Data!$D$2:$D$1501) | J19: =SUM($H$14:H19)
G20: 2023-07 | H20: =SUMIF(Data!$T$2:$T$1501,"2023-07",Data!$J$2:$J$1501) | I20: =SUMIF(Data!$T$2:$T$1501,"2023-07",Data!$D$2:$D$1501) | J20: =SUM($H$14:H20)
G21: 2023-08 | H21: =SUMIF(Data!$T$2:$T$1501,"2023-08",Data!$J$2:$J$1501) | I21: =SUMIF(Data!$T$2:$T$1501,"2023-08",Data!$D$2:$D$1501) | J21: =SUM($H$14:H21)
G22: 2023-09 | H22: =SUMIF(Data!$T$2:$T$1501,"2023-09",Data!$J$2:$J$1501) | I22: =SUMIF(Data!$T$2:$T$1501,"2023-09",Data!$D$2:$D$1501) | J22: =SUM($H$14:H22)
G23: 2023-10 | H23: =SUMIF(Data!$T$2:$T$1501,"2023-10",Data!$J$2:$J$1501) | I23: =SUMIF(Data!$T$2:$T$1501,"2023-10",Data!$D$2:$D$1501) | J23: =SUM($H$14:H23)
G24: 2023-11 | H24: =SUMIF(Data!$T$2:$T$1501,"2023-11",Data!$J$2:$J$1501) | I24: =SUMIF(Data!$T$2:$T$1501,"2023-11",Data!$D$2:$D$1501) | J24: =SUM($H$14:H24)
G25: 2023-12 | H25: =SUMIF(Data!$T$2:$T$1501,"2023-12",Data!$J$2:$J$1501) | I25: =SUMIF(Data!$T$2:$T$1501,"2023-12",Data!$D$2:$D$1501) | J25: =SUM($H$14:H25)
G26: 2024-01 | H26: =SUMIF(Data!$T$2:$T$1501,"2024-01",Data!$J$2:$J$1501) | I26: =SUMIF(Data!$T$2:$T$1501,"2024-01",Data!$D$2:$D$1501) | J26: =SUM($H$14:H26)
G27: 2024-02 | H27: =SUMIF(Data!$T$2:$T$1501,"2024-02",Data!$J$2:$J$1501) | I27: =SUMIF(Data!$T$2:$T$1501,"2024-02",Data!$D$2:$D$1501) | J27: =SUM($H$14:H27)
G28: 2024-03 | H28: =SUMIF(Data!$T$2:$T$1501,"2024-03",Data!$J$2:$J$1501) | I28: =SUMIF(Data!$T$2:$T$1501,"2024-03",Data!$D$2:$D$1501) | J28: =SUM($H$14:H28)
G29: 2024-04 | H29: =SUMIF(Data!$T$2:$T$1501,"2024-04",Data!$J$2:$J$1501) | I29: =SUMIF(Data!$T$2:$T$1501,"2024-04",Data!$D$2:$D$1501) | J29: =SUM($H$14:H29)
G30: 2024-05 | H30: =SUMIF(Data!$T$2:$T$1501,"2024-05",Data!$J$2:$J$1501) | I30: =SUMIF(Data!$T$2:$T$1501,"2024-05",Data!$D$2:$D$1501) | J30: =SUM($H$14:H30)
G31: 2024-06 | H31: =SUMIF(Data!$T$2:$T$1501,"2024-06",Data!$J$2:$J$1501) | I31: =SUMIF(Data!$T$2:$T$1501,"2024-06",Data!$D$2:$D$1501) | J31: =SUM($H$14:H31)
G32: 2024-07 | H32: =SUMIF(Data!$T$2:$T$1501,"2024-07",Data!$J$2:$J$1501) | I32: =SUMIF(Data!$T$2:$T$1501,"2024-07",Data!$D$2:$D$1501) | J32: =SUM($H$14:H32)
G33: 2024-08 | H33: =SUMIF(Data!$T$2:$T$1501,"2024-08",Data!$J$2:$J$1501) | I33: =SUMIF(Data!$T$2:$T$1501,"2024-08",Data!$D$2:$D$1501) | J33: =SUM($H$14:H33)
G34: 2024-09 | H34: =SUMIF(Data!$T$2:$T$1501,"2024-09",Data!$J$2:$J$1501) | I34: =SUMIF(Data!$T$2:$T$1501,"2024-09",Data!$D$2:$D$1501) | J34: =SUM($H$14:H34)
G35: 2024-10 | H35: =SUMIF(Data!$T$2:$T$1501,"2024-10",Data!$J$2:$J$1501) | I35: =SUMIF(Data!$T$2:$T$1501,"2024-10",Data!$D$2:$D$1501) | J35: =SUM($H$14:H35)
G36: 2024-11 | H36: =SUMIF(Data!$T$2:$T$1501,"2024-11",Data!$J$2:$J$1501) | I36: =SUMIF(Data!$T$2:$T$1501,"2024-11",Data!$D$2:$D$1501) | J36: =SUM($H$14:H36)
G37: 2024-12 | H37: =SUMIF(Data!$T$2:$T$1501,"2024-12",Data!$J$2:$J$1501) | I37: =SUMIF(Data!$T$2:$T$1501,"2024-12",Data!$D$2:$D$1501) | J37: =SUM($H$14:H37)
G38: 2025-01 | H38: =SUMIF(Data!$T$2:$T$1501,"2025-01",Data!$J$2:$J$1501) | I38: =SUMIF(Data!$T$2:$T$1501,"2025-01",Data!$D$2:$D$1501) | J38: =SUM($H$14:H38)
G39: 2025-02 | H39: =SUMIF(Data!$T$2:$T$1501,"2025-02",Data!$J$2:$J$1501) | I39: =SUMIF(Data!$T$2:$T$1501,"2025-02",Data!$D$2:$D$1501) | J39: =SUM($H$14:H39)
G40: Scatter Sample X=UnitPrice Y=Qty | H40: =SUMIF(Data!$T$2:$T$1501,"2025-03",Data!$J$2:$J$1501) | I40: =SUMIF(Data!$T$2:$T$1501,"2025-03",Data!$D$2:$D$1501) | J40: =SUM($H$14:H40)
G41: UnitPrice | H41: Quantity | I41: =SUMIF(Data!$T$2:$T$1501,"2025-04",Data!$D$2:$D$1501) | J41: =SUM($H$14:H41)
G42: 423.64 | H42: 13 | I42: =SUMIF(Data!$T$2:$T$1501,"2025-05",Data!$D$2:$D$1501) | J42: =SUM($H$14:H42)
G43: 304.15 | H43: 8 | I43: =SUMIF(Data!$T$2:$T$1501,"2025-06",Data!$D$2:$D$1501) | J43: =SUM($H$14:H43)
G44: 448.13 | H44: 19
G45: 478.73 | H45: 19
G46: 599.72 | H46: 3
G47: 367.61 | H47: 5
G48: 300.38 | H48: 14
G49: 549.78 | H49: 17
G50: 574.32 | H50: 14
G51: 50.26 | H51: 7
G52: 152.75 | H52: 1
G53: 346.86 | H53: 6
G54: 507.74 | H54: 9
G55: 78.05 | H55: 4
... G141: 484.38 | H141: 14

Sheet Instructions
A1: AUDITED 5.2 - ZERO REF - PLAIN RANGE FORMULAS
A3: Previous used SalesData[Region] structured refs - some Excel versions show #REF if table not recalculated
A4: Now all formulas use plain ranges: =SUMIF(Data!B2:B1501,"East",Data!J2:J1501) - never #REF
A5: YearMonth helper column T in Data sheet = date formatted yyyy-mm, used for monthly charts
A6: KPI cards: =SUM(Data!J2:J1501) etc - connected, if Data changes, dashboard updates
A7: Charts point to Analytics which has plain SUMIF formulas - all connected
A8: Full Screen: Press Alt+W then L (View>Full Screen) or add VBA: Sub ToggleFullScreen() Application.DisplayFullScreen = Not Application.DisplayFullScreen: End Sub
A9: Neat arrangement: 3 charts per row, 13 width, colorful, header full width
